livekit/plugins/openai/__init__.py
livekit/plugins/openai/embeddings.py
livekit/plugins/openai/llm.py
livekit/plugins/openai/log.py
livekit/plugins/openai/models.py
livekit/plugins/openai/py.typed
livekit/plugins/openai/stt.py
livekit/plugins/openai/tts.py
livekit/plugins/openai/utils.py
livekit/plugins/openai/version.py
livekit/plugins/openai/realtime/__init__.py
livekit/plugins/openai/realtime/realtime_model.py
livekit/plugins/openai/realtime/realtime_model_beta.py
livekit/plugins/openai/realtime/utils.py
livekit_plugins_openai-1.3.8.dist-info/METADATA
livekit_plugins_openai-1.3.8.dist-info/WHEEL
livekit_plugins_openai-1.3.8.dist-info/RECORD
