Metadata-Version: 2.4
Name: livekit-plugins-openai
Version: 1.3.8
Summary: Agent Framework plugin for services from OpenAI
Project-URL: Documentation, https://docs.livekit.io
Project-URL: Website, https://livekit.io/
Project-URL: Source, https://github.com/livekit/agents
Author-email: LiveKit <hello@livekit.io>
License-Expression: Apache-2.0
Keywords: ai,audio,livekit,openai,realtime,video,voice
Classifier: Intended Audience :: Developers
Classifier: License :: OSI Approved :: Apache Software License
Classifier: Programming Language :: Python :: 3
Classifier: Programming Language :: Python :: 3 :: Only
Classifier: Programming Language :: Python :: 3.9
Classifier: Programming Language :: Python :: 3.10
Classifier: Topic :: Multimedia :: Sound/Audio
Classifier: Topic :: Multimedia :: Video
Classifier: Topic :: Scientific/Engineering :: Artificial Intelligence
Requires-Python: >=3.9.0
Requires-Dist: livekit-agents[codecs,images]>=1.3.8
Requires-Dist: openai[realtime]>=1.107.2
Provides-Extra: vertex
Requires-Dist: google-auth>=2.0.0; extra == 'vertex'
